setup.py
smtphandler_backport/__init__.py
smtphandler_backport.egg-info/PKG-INFO
smtphandler_backport.egg-info/SOURCES.txt
smtphandler_backport.egg-info/dependency_links.txt
smtphandler_backport.egg-info/top_level.txt