Metadata-Version: 1.0
Name: smtphandler-backport
Version: 0.01
Summary: Backport to Python 2.6 of the SMTPHandler in higher versions.
Home-page: https://github.com/afroisalreadyinu/smtphandler_backport
Author: Ulas Tuerkmen
Author-email: ulas.tuerkmen@gmail.com
License: UNKNOWN
Platform: UNKNOWN
